{
  "$schema": "https://ukiyoue.example.org/schemas/layer1/data-dictionary.json",
  "@context": "https://ukiyoue.example.org/context/data-dictionary.jsonld",
  "@type": "DataDictionary",
  "id": "dict-tos-001",
  "title": "Table Order System - Data Dictionary",
  "description": "Defines business and technical terminology used across the Table Order System",
  "traceability": {
    "derivedFrom": []
  },
  "terms": [
    {
      "id": "TERM-TOS-001",
      "term": "Order",
      "canonicalName": "Order",
      "description": "A customer's request for food and beverages submitted through the tablet interface",
      "synonyms": ["注文", "オーダー", "Customer Order"],
      "domain": "business",
      "layer": "conceptual",
      "dataType": "Object",
      "constraints": {
        "required": true
      },
      "relatedTerms": ["TERM-TOS-002", "TERM-TOS-003", "TERM-TOS-004"],
      "examples": ["Order #42: Table 5, 2x Margherita Pizza"],
      "tags": ["core-entity", "transactional"],
      "deprecated": false
    },
    {
      "id": "TERM-TOS-002",
      "term": "Order ID",
      "canonicalName": "OrderId",
      "description": "Unique identifier for an order, automatically generated by the system",
      "synonyms": ["Order Number", "注文番号", "オーダーID"],
      "domain": "system",
      "layer": "logical",
      "dataType": "UUID",
      "constraints": {
        "required": true,
        "unique": true,
        "pattern": "^[0-9a-f]{8}-[0-9a-f]{4}-4[0-9a-f]{3}-[89ab][0-9a-f]{3}-[0-9a-f]{12}$"
      },
      "examples": ["550e8400-e29b-41d4-a716-446655440000"],
      "tags": ["identifier", "primary-key"],
      "deprecated": false
    },
    {
      "id": "TERM-TOS-003",
      "term": "Menu",
      "canonicalName": "Menu",
      "description": "Collection of available food and beverage items organized by category",
      "synonyms": ["メニュー", "Menu List"],
      "domain": "business",
      "layer": "conceptual",
      "dataType": "Object",
      "constraints": {
        "required": true
      },
      "relatedTerms": ["TERM-TOS-005"],
      "examples": ["Lunch Menu: Pizzas, Pastas, Salads, Desserts"],
      "tags": ["core-entity", "catalog"],
      "deprecated": false
    },
    {
      "id": "TERM-TOS-004",
      "term": "Table",
      "canonicalName": "Table",
      "description": "Physical dining table with unique identifier for order placement",
      "synonyms": ["テーブル", "Dining Table", "卓"],
      "domain": "business",
      "layer": "conceptual",
      "dataType": "Object",
      "constraints": {
        "required": true
      },
      "relatedTerms": ["TERM-TOS-006"],
      "examples": ["Table 5 (capacity: 4 seats)"],
      "tags": ["core-entity", "physical-location"],
      "deprecated": false
    },
    {
      "id": "TERM-TOS-005",
      "term": "Menu Item",
      "canonicalName": "MenuItem",
      "description": "Individual food or beverage item with name, price, and description",
      "synonyms": ["Item", "Dish", "料理", "メニュー項目"],
      "domain": "business",
      "layer": "conceptual",
      "dataType": "Object",
      "constraints": {
        "required": true
      },
      "relatedTerms": ["TERM-TOS-003"],
      "examples": ["Margherita Pizza - Classic tomato, mozzarella, basil - $12.99"],
      "tags": ["entity", "product"],
      "deprecated": false
    },
    {
      "id": "TERM-TOS-006",
      "term": "Table Number",
      "canonicalName": "TableNumber",
      "description": "Unique numeric identifier for a dining table",
      "synonyms": ["Table ID", "テーブル番号", "卓番号"],
      "domain": "system",
      "layer": "logical",
      "dataType": "Integer",
      "constraints": {
        "required": true,
        "unique": true,
        "minimum": 1,
        "maximum": 100
      },
      "examples": ["5", "12", "42"],
      "tags": ["identifier", "natural-key"],
      "deprecated": false
    },
    {
      "id": "TERM-TOS-007",
      "term": "Customer",
      "canonicalName": "Customer",
      "description": "Person dining at the restaurant who places orders",
      "synonyms": ["お客様", "顧客", "Guest", "Diner"],
      "domain": "business",
      "layer": "conceptual",
      "dataType": "Object",
      "constraints": {
        "required": false
      },
      "relatedTerms": ["TERM-TOS-001", "TERM-TOS-004"],
      "examples": ["Walk-in customer at Table 5"],
      "tags": ["entity", "actor"],
      "deprecated": false
    },
    {
      "id": "TERM-TOS-008",
      "term": "Order Status",
      "canonicalName": "OrderStatus",
      "description": "Current state of an order in its lifecycle",
      "synonyms": ["Status", "注文ステータス", "State"],
      "domain": "system",
      "layer": "logical",
      "dataType": "Enum",
      "constraints": {
        "required": true,
        "allowedValues": ["PENDING", "PREPARING", "READY", "COMPLETED", "CANCELLED"]
      },
      "examples": ["PREPARING", "READY", "COMPLETED"],
      "tags": ["state", "enum"],
      "deprecated": false
    },
    {
      "id": "TERM-TOS-009",
      "term": "Category",
      "canonicalName": "Category",
      "description": "Grouping of menu items by type (e.g., Pizza, Pasta, Dessert)",
      "synonyms": ["カテゴリー", "Menu Category", "分類"],
      "domain": "business",
      "layer": "conceptual",
      "dataType": "String",
      "constraints": {
        "required": true,
        "maxLength": 50
      },
      "examples": ["Pizza", "Pasta", "Salad", "Dessert", "Beverage"],
      "tags": ["classification", "taxonomy"],
      "deprecated": false
    },
    {
      "id": "TERM-TOS-010",
      "term": "Guest",
      "canonicalName": "Guest",
      "description": "Deprecated term for Customer. Use 'Customer' instead.",
      "synonyms": ["ゲスト"],
      "domain": "business",
      "layer": "conceptual",
      "dataType": "Object",
      "constraints": {
        "required": false
      },
      "tags": ["deprecated-term"],
      "deprecated": true,
      "replacedBy": "TERM-TOS-007"
    }
  ]
}
